PyBackup_Tool.py
pybackup_tool-1.0.0.dist-info/licenses/LICENSE
pybackup_tool-1.0.0.dist-info/METADATA
pybackup_tool-1.0.0.dist-info/WHEEL
pybackup_tool-1.0.0.dist-info/entry_points.txt
pybackup_tool-1.0.0.dist-info/top_level.txt
pybackup_tool-1.0.0.dist-info/RECORD
