Metadata-Version: 2.4
Name: PyBackup-Tool
Version: 1.0.0
Summary: Zero-dependency Python backup tool with configuration file support
Home-page: https://github.com/ByteStackr/PyBackup-Tool
Author: ByteStackr
Author-email: ByteStackr <229177070+ByteStackr@users.noreply.github.com>
Maintainer-email: ByteStackr <229177070+ByteStackr@users.noreply.github.com>
License: MIT
Project-URL: Homepage, https://github.com/ByteStackr/PyBackup-Tool
Project-URL: Bug Tracker, https://github.com/ByteStackr/PyBackup-Tool/issues
Project-URL: Repository, https://github.com/ByteStackr/PyBackup-Tool.git
Project-URL: Documentation, https://github.com/ByteStackr/PyBackup-Tool#readme
Keywords: backup,cli,tool,zero-dependency,configuration
Classifier: Development Status :: 5 - Production/Stable
Classifier: Intended Audience :: Developers
Classifier: License :: OSI Approved :: MIT License
Classifier: Operating System :: OS Independent
Classifier: Programming Language :: Python :: 3
Classifier: Programming Language :: Python :: 3.6
Classifier: Programming Language :: Python :: 3.7
Classifier: Programming Language :: Python :: 3.8
Classifier: Programming Language :: Python :: 3.9
Classifier: Programming Language :: Python :: 3.10
Classifier: Programming Language :: Python :: 3.11
Classifier: Programming Language :: Python :: 3.12
Classifier: Topic :: System :: Archiving :: Backup
Classifier: Topic :: Utilities
Requires-Python: >=3.6
License-File: LICENSE
Dynamic: author
Dynamic: home-page
Dynamic: license-file
Dynamic: requires-python
